cleanvid/__init__.py
cleanvid/caselessdictionary.py
cleanvid/cleanvid.py
cleanvid/swears.txt
cleanvid-1.7.0.dist-info/LICENSE
cleanvid-1.7.0.dist-info/METADATA
cleanvid-1.7.0.dist-info/WHEEL
cleanvid-1.7.0.dist-info/entry_points.txt
cleanvid-1.7.0.dist-info/top_level.txt
cleanvid-1.7.0.dist-info/RECORD
