Metadata-Version: 2.1
Name: cleanvid
Version: 1.7.0
Summary: cleanvid is a little script to mute profanity in video files.
Home-page: https://github.com/mmguero/cleanvid
Author: Seth Grover
Author-email: mero.mero.guero@gmail.com
Project-URL: Bug Tracker, https://github.com/mmguero/cleanvid/issues
Classifier: License :: OSI Approved :: BSD License
Classifier: Operating System :: OS Independent
Classifier: Programming Language :: Python :: 3
Classifier: Topic :: Multimedia :: Video
Requires-Python: >=3.6
License-File: LICENSE
Requires-Dist: babelfish
Requires-Dist: delegator.py
Requires-Dist: pysrt
Requires-Dist: subliminal
